{"data_pageName":"","style_bgAlpha":100,"data_shoppingFloat":"","item":[{"style_textSize":30,"style_textAlign":1,"sys_moduleType":3,"sys_z":0,"sys_w":140,"sys_y":0,"style_textAlpha":"100","sys_x":117,"style_textColor":"FFFFFF","style_galleryTextAlpha":"100","data_text":"资料属性","style_textBold":0,"sys_h":40},{"nPageId":null,"style_bgAlpha":100,"style_textSize":13,"style_textAlign":1,"sys_moduleType":1,"sys_z":1,"sys_w":100,"sys_y":5,"style_textAlpha":"100","sys_x":7,"nPageType":2,"style_textColor":"FFFFFF","nFlag":1,"style_galleryTextAlpha":"100","data_text":"上一页","style_bgType":1,"style_bgPic":"","style_textBold":0,"style_bgColor":"1DC6F1","sys_h":30},{"nPageId":"e9211290-7a99-48e6-af3a-75fb72567b1b","data_pic":"1614267386040_505215.png","style_bigPic":"","sys_moduleType":2,"sys_z":2,"nFlag":1,"sys_w":60,"sys_y":50,"sys_x":7,"sys_h":60,"nPageType":0,"style_eventType":"2"},{"nPageId":"3d7b1053-8dd8-424e-870d-d7107513d8cd","data_pic":"1614267386219_584588.png","style_bigPic":"","sys_moduleType":2,"sys_z":3,"nFlag":1,"sys_w":60,"sys_y":50,"sys_x":67,"sys_h":60,"nPageType":0,"style_eventType":"2"},{"nPageId":"bd77cff3-8e3d-47a2-b733-b185063f5325","data_pic":"1614267386357_425054.png","style_bigPic":"","sys_moduleType":2,"sys_z":4,"nFlag":1,"sys_w":60,"sys_y":50,"sys_x":127,"sys_h":60,"nPageType":0,"style_eventType":"2"},{"nPageId":"7d250543-ef1c-4fd9-b1b7-a56d4766100e","data_pic":"1614267386539_665392.png","style_bigPic":"","sys_moduleType":2,"sys_z":5,"nFlag":1,"sys_w":60,"sys_y":50,"sys_x":187,"sys_h":60,"nPageType":0,"style_eventType":"2"},{"nPageId":"b7a3e351-76af-4d4c-867e-017733fb9900","data_pic":"1614697986768_631358.png","style_bigPic":"","sys_moduleType":2,"sys_z":6,"nFlag":1,"sys_w":60,"sys_y":50,"sys_x":247,"sys_h":60,"nPageType":0,"style_eventType":"2"},{"nPageId":"d84220f1-400f-4f2f-b022-3afffac1295a","data_pic":"1614618485537_988260.png","style_bigPic":"","sys_moduleType":2,"sys_z":7,"nFlag":1,"sys_w":60,"sys_y":50,"sys_x":307,"sys_h":60,"nPageType":0,"style_eventType":"2"},{"nPageId":"dca05e11-53f8-4259-9028-2cdf2e773d79","data_pic":"1614618495118_257171.png","style_bigPic":"","sys_moduleType":2,"sys_z":8,"nFlag":1,"sys_w":60,"sys_y":110,"sys_x":7,"sys_h":60,"nPageType":0,"style_eventType":"2"},{"nPageId":"6325d870-37a7-4e50-a2ae-b4247eec3d21","data_pic":"1614618495221_810685.png","style_bigPic":"","sys_moduleType":2,"sys_z":9,"nFlag":1,"sys_w":60,"sys_y":110,"sys_x":67,"sys_h":60,"nPageType":0,"style_eventType":"2"},{"nPageId":"e1483037-6088-49ae-b18c-77392945215a","data_pic":"1614618495370_570563.png","style_bigPic":"","sys_moduleType":2,"sys_z":10,"nFlag":1,"sys_w":60,"sys_y":110,"sys_x":127,"sys_h":60,"nPageType":0,"style_eventType":"2"},{"nPageId":"4f9f276d-ab81-47b3-8505-5fae34bc2e9a","data_pic":"1614618495474_333269.png","style_bigPic":"","sys_moduleType":2,"sys_z":11,"nFlag":1,"sys_w":60,"sys_y":110,"sys_x":187,"sys_h":60,"nPageType":0,"style_eventType":"2"},{"nPageId":"e0cc92f3-0756-4cc9-ba4e-c12c7fa0905c","data_pic":"1614697997877_590702.png","style_bigPic":"","sys_moduleType":2,"sys_z":12,"nFlag":1,"sys_w":60,"sys_y":110,"sys_x":247,"sys_h":60,"nPageType":0,"style_eventType":"2"},{"nPageId":"b04469b9-d5aa-4bb1-8eff-2f45ef7af575","data_pic":"1614698509881_1008635.png","style_bigPic":"","sys_moduleType":2,"sys_z":13,"nFlag":1,"sys_w":60,"sys_y":110,"sys_x":307,"sys_h":60,"nPageType":0,"style_eventType":"2"},{"nPageId":"412d846d-21bd-4527-9412-319d8bdac5f5","data_pic":"1614698518757_677041.png","style_bigPic":"","sys_moduleType":2,"sys_z":14,"nFlag":1,"sys_w":60,"sys_y":170,"sys_x":7,"sys_h":60,"nPageType":0,"style_eventType":"2"},{"nPageId":"f23bb4f5-1a6b-4498-916e-bbdb57a8c434","data_pic":"1614698518859_128102.png","style_bigPic":"","sys_moduleType":2,"sys_z":15,"nFlag":1,"sys_w":60,"sys_y":170,"sys_x":67,"sys_h":60,"nPageType":0,"style_eventType":"2"},{"nPageId":"0b160d5d-e844-4919-b136-7e84d0772151","data_pic":"1614698518960_722269.png","style_bigPic":"","sys_moduleType":2,"sys_z":16,"nFlag":1,"sys_w":60,"sys_y":170,"sys_x":127,"sys_h":60,"nPageType":0,"style_eventType":"2"},{"nPageId":"586e96cd-9aa5-48cc-86a8-3f58649e4dc0","data_pic":"1614698526874_389444.png","style_bigPic":"","sys_moduleType":2,"sys_z":17,"nFlag":1,"sys_w":60,"sys_y":170,"sys_x":187,"sys_h":60,"nPageType":0,"style_eventType":"2"},{"nPageId":"5f734374-9778-4fb1-917b-af22983dd858","data_pic":"1614698543470_265958.png","style_bigPic":"","sys_moduleType":2,"sys_z":18,"nFlag":1,"sys_w":60,"sys_y":170,"sys_x":247,"sys_h":60,"nPageType":0,"style_eventType":"2"},{"nPageId":"b22c401b-42cc-482d-b98a-816b70007654","data_pic":"1614698543563_756623.png","style_bigPic":"","sys_moduleType":2,"sys_z":19,"nFlag":1,"sys_w":60,"sys_y":170,"sys_x":307,"sys_h":60,"nPageType":0,"style_eventType":"2"},{"nPageId":"","data_pic":"1614698518757_677041.png","style_bigPic":"","sys_moduleType":2,"sys_z":20,"nFlag":0,"sys_w":25,"sys_y":205,"sys_x":187,"sys_h":25,"nPageType":0,"style_eventType":"2"},{"nPageId":"7b75ede9-fd12-4ae7-a32e-2f3947365a86","data_pic":"1614698543673_943695.png","style_bigPic":"","sys_moduleType":2,"sys_z":21,"nFlag":1,"sys_w":60,"sys_y":230,"sys_x":7,"sys_h":60,"nPageType":0,"style_eventType":"2"},{"nPageId":"","data_pic":"1614698518757_677041.png","style_bigPic":"","sys_moduleType":2,"sys_z":22,"nFlag":0,"sys_w":25,"sys_y":145,"sys_x":342,"sys_h":25,"nPageType":0,"style_eventType":"2"},{"nPageId":"e37a7476-4760-4d50-8570-0bf99c6f976b","data_pic":"1614698509881_1008635.png","style_bigPic":"","sys_moduleType":2,"sys_z":23,"nFlag":1,"sys_w":60,"sys_y":230,"sys_x":67,"sys_h":60,"nPageType":0,"style_eventType":"2"},{"nPageId":"","data_pic":"1614265676128_1092672.png","style_bigPic":"","sys_moduleType":2,"sys_z":24,"nFlag":0,"sys_w":25,"sys_y":265,"sys_x":102,"sys_h":25,"nPageType":0,"style_eventType":"2"},{"nPageId":"9c0010fd-32bc-45ed-b64b-25780e928f16","data_pic":"1614698526874_389444.png","style_bigPic":"","sys_moduleType":2,"sys_z":25,"nFlag":1,"sys_w":60,"sys_y":230,"sys_x":127,"sys_h":60,"nPageType":0,"style_eventType":"2"},{"nPageId":"cfca8661-cdc9-49b2-812b-18ba47748384","data_pic":"1614698509881_1008635.png","style_bigPic":"","sys_moduleType":2,"sys_z":26,"nFlag":1,"sys_w":60,"sys_y":230,"sys_x":187,"sys_h":60,"nPageType":0,"style_eventType":"2"},{"nPageId":"","data_pic":"1614698543774_611786.png","style_bigPic":"","sys_moduleType":2,"sys_z":27,"nFlag":0,"sys_w":25,"sys_y":265,"sys_x":222,"sys_h":25,"nPageType":0,"style_eventType":"2"},{"nPageId":"e0d344b1-cf67-406f-91dd-e93badd2541f","data_pic":"1614698526874_389444.png","style_bigPic":"","sys_moduleType":2,"sys_z":28,"nFlag":1,"sys_w":60,"sys_y":230,"sys_x":247,"sys_h":60,"nPageType":0,"style_eventType":"2"},{"nPageId":"537ee59c-e422-4103-8777-4ea76044cf90","data_pic":"1614618342814_163560.png","style_bigPic":"","sys_moduleType":2,"sys_z":29,"nFlag":1,"sys_w":60,"sys_y":230,"sys_x":307,"sys_h":60,"nPageType":0,"style_eventType":"2"},{"nPageId":"6fc8e3ff-048c-4080-921b-7d1fb421a141","data_pic":"1614618343071_1001740.png","style_bigPic":"","sys_moduleType":2,"sys_z":30,"nFlag":1,"sys_w":60,"sys_y":290,"sys_x":7,"sys_h":60,"nPageType":0,"style_eventType":"2"},{"nPageId":"e6f97035-255f-4149-a657-a3371cb2e3da","data_pic":"1614618343183_772447.png","style_bigPic":"","sys_moduleType":2,"sys_z":31,"nFlag":1,"sys_w":60,"sys_y":290,"sys_x":67,"sys_h":60,"nPageType":0,"style_eventType":"2"},{"nPageId":"7352d223-6cb3-4ad8-9740-9296a56e9239","data_pic":"1614618362836_494350.png","style_bigPic":"","sys_moduleType":2,"sys_z":32,"nFlag":1,"sys_w":60,"sys_y":290,"sys_x":127,"sys_h":60,"nPageType":0,"style_eventType":"2"},{"nPageId":"e97dbe35-d384-40e8-a7ea-aa9d8ca39263","data_pic":"1614618363089_834669.png","style_bigPic":"","sys_moduleType":2,"sys_z":33,"nFlag":1,"sys_w":60,"sys_y":290,"sys_x":187,"sys_h":60,"nPageType":0,"style_eventType":"2"},{"nPageId":"52354cee-4616-427d-bc5a-1011fdd9e5dd","data_pic":"1614698061455_226034.png","style_bigPic":"","sys_moduleType":2,"sys_z":34,"nFlag":1,"sys_w":60,"sys_y":290,"sys_x":247,"sys_h":60,"nPageType":0,"style_eventType":"2"},{"nPageId":"28b630d2-6429-46bc-a5d8-9197102d352d","data_pic":"1614698084445_316474.png","style_bigPic":"","sys_moduleType":2,"sys_z":35,"nFlag":1,"sys_w":60,"sys_y":290,"sys_x":307,"sys_h":60,"nPageType":0,"style_eventType":"2"},{"nPageId":"335de899-602a-484d-a90f-3a70a0c0b730","data_pic":"1614267420702_1089521.png","style_bigPic":"","sys_moduleType":2,"sys_z":36,"nFlag":1,"sys_w":60,"sys_y":530,"sys_x":307,"sys_h":60,"nPageType":0,"style_eventType":"2"},{"nPageId":"70a0be8a-afb0-4604-929a-b53efd57fa76","data_pic":"1614267436668_545313.png","style_bigPic":"","sys_moduleType":2,"sys_z":37,"nFlag":1,"sys_w":60,"sys_y":590,"sys_x":7,"sys_h":60,"nPageType":0,"style_eventType":"2"},{"nPageId":"ba988533-81dc-4cdc-941a-e61463f5e63d","data_pic":"1614267436795_474740.png","style_bigPic":"","sys_moduleType":2,"sys_z":38,"nFlag":1,"sys_w":60,"sys_y":590,"sys_x":67,"sys_h":60,"nPageType":0,"style_eventType":"2"},{"nPageId":"","data_pic":"1614698216310_934957.png","style_bigPic":"","sys_moduleType":2,"sys_z":39,"nFlag":0,"sys_w":25,"sys_y":625,"sys_x":102,"sys_h":25,"nPageType":0,"style_eventType":"2"},{"nPageId":"fe8929e8-2134-4205-a2d2-de48ed82fa90","data_pic":"1614267475650_327415.png","style_bigPic":"","sys_moduleType":2,"sys_z":40,"nFlag":1,"sys_w":60,"sys_y":590,"sys_x":127,"sys_h":60,"nPageType":0,"style_eventType":"2"},{"nPageId":"ebc3c2c3-15fc-4851-95cc-374f4007814f","data_pic":"1614267475935_523815.png","style_bigPic":"","sys_moduleType":2,"sys_z":41,"nFlag":1,"sys_w":60,"sys_y":590,"sys_x":187,"sys_h":60,"nPageType":0,"style_eventType":"2"},{"nPageId":"f4d0164e-da62-45fa-8306-3083bd137114","data_pic":"1614267476192_396460.png","style_bigPic":"","sys_moduleType":2,"sys_z":42,"nFlag":1,"sys_w":60,"sys_y":590,"sys_x":247,"sys_h":60,"nPageType":0,"style_eventType":"2"},{"nPageId":"c7f1efbc-8935-4686-ad53-1af53ca97b63","data_pic":"1614267420702_1089521.png","style_bigPic":"","sys_moduleType":2,"sys_z":43,"nFlag":1,"sys_w":60,"sys_y":350,"sys_x":247,"sys_h":60,"nPageType":0,"style_eventType":"2"},{"nPageId":"833e9c7c-f4b4-4100-ba2e-d42b798d52ef","data_pic":"1614267436668_545313.png","style_bigPic":"","sys_moduleType":2,"sys_z":44,"nFlag":1,"sys_w":60,"sys_y":350,"sys_x":307,"sys_h":60,"nPageType":0,"style_eventType":"2"},{"nPageId":"","data_pic":"1614618363754_699326.png","style_bigPic":"","sys_moduleType":2,"sys_z":45,"nFlag":0,"sys_w":25,"sys_y":385,"sys_x":282,"sys_h":25,"nPageType":0,"style_eventType":"2"},{"nPageId":"95e3b2df-8745-4993-ae7f-478ffd2f8f57","data_pic":"1614267436795_474740.png","style_bigPic":"","sys_moduleType":2,"sys_z":46,"nFlag":1,"sys_w":60,"sys_y":410,"sys_x":7,"sys_h":60,"nPageType":0,"style_eventType":"2"},{"nPageId":"","data_pic":"1614618363754_699326.png","style_bigPic":"","sys_moduleType":2,"sys_z":47,"nFlag":0,"sys_w":25,"sys_y":385,"sys_x":342,"sys_h":25,"nPageType":0,"style_eventType":"2"},{"nPageId":"cce2f001-82dd-44b7-9b2c-be7b3c4760bd","data_pic":"1614265080730_985087.png","style_bigPic":"","sys_moduleType":2,"sys_z":48,"nFlag":1,"sys_w":60,"sys_y":410,"sys_x":67,"sys_h":60,"nPageType":0,"style_eventType":"2"},{"nPageId":"32146666-571c-49df-9dcf-c1a92820539d","data_pic":"1614267436938_183219.png","style_bigPic":"","sys_moduleType":2,"sys_z":49,"nFlag":1,"sys_w":60,"sys_y":410,"sys_x":127,"sys_h":60,"nPageType":0,"style_eventType":"2"},{"nPageId":"0823244c-7076-4c63-a2ae-a354f9bfe8c8","data_pic":"1614267437118_813371.png","style_bigPic":"","sys_moduleType":2,"sys_z":50,"nFlag":1,"sys_w":60,"sys_y":410,"sys_x":187,"sys_h":60,"nPageType":0,"style_eventType":"2"},{"nPageId":"39971e2b-7a3b-4032-8061-48c58e8c1467","data_pic":"1614698609984_336261.png","style_bigPic":"","sys_moduleType":2,"sys_z":51,"nFlag":1,"sys_w":60,"sys_y":470,"sys_x":247,"sys_h":60,"nPageType":0,"style_eventType":"2"},{"nPageId":"","data_pic":"1614698609852_978390.png","style_bigPic":"","sys_moduleType":2,"sys_z":52,"nFlag":0,"sys_w":25,"sys_y":505,"sys_x":282,"sys_h":25,"nPageType":0,"style_eventType":"2"},{"nPageId":"4c49fad3-c46c-46c3-96f6-87b7d310d41c","data_pic":"1614698618049_102394.png","style_bigPic":"","sys_moduleType":2,"sys_z":53,"nFlag":1,"sys_w":60,"sys_y":470,"sys_x":307,"sys_h":60,"nPageType":0,"style_eventType":"2"},{"nPageId":"8b09aa8a-9a19-42d7-856e-abeea2b78c49","data_pic":"1614698609984_336261.png","style_bigPic":"","sys_moduleType":2,"sys_z":54,"nFlag":1,"sys_w":60,"sys_y":530,"sys_x":7,"sys_h":60,"nPageType":0,"style_eventType":"2"},{"nPageId":"","data_pic":"1614698618049_102394.png","style_bigPic":"","sys_moduleType":2,"sys_z":55,"nFlag":0,"sys_w":25,"sys_y":565,"sys_x":42,"sys_h":25,"nPageType":0,"style_eventType":"2"},{"nPageId":"dbe8580d-b20f-4002-af8d-20111239c4a3","data_pic":"1614698637476_172685.png","style_bigPic":"","sys_moduleType":2,"sys_z":56,"nFlag":1,"sys_w":60,"sys_y":530,"sys_x":67,"sys_h":60,"nPageType":0,"style_eventType":"2"},{"nPageId":"68548175-af1b-4f21-9c28-42b4e4a4a981","data_pic":"1614698637659_809284.png","style_bigPic":"","sys_moduleType":2,"sys_z":57,"nFlag":1,"sys_w":60,"sys_y":530,"sys_x":127,"sys_h":60,"nPageType":0,"style_eventType":"2"},{"nPageId":"961bcec3-25dc-4a08-9dc5-f122fdbafad6","data_pic":"1614780121934_171678.png","style_bigPic":"","sys_moduleType":2,"sys_z":58,"nFlag":1,"sys_w":60,"sys_y":530,"sys_x":187,"sys_h":60,"nPageType":0,"style_eventType":"2"},{"nPageId":"91cfd1d2-2a74-440f-b742-5dc3474591f5","data_pic":"1614698637887_392025.png","style_bigPic":"","sys_moduleType":2,"sys_z":59,"nFlag":1,"sys_w":60,"sys_y":530,"sys_x":247,"sys_h":60,"nPageType":0,"style_eventType":"2"},{"nPageId":"0d79ee00-612f-4749-b89a-00c9612f68f9","data_pic":"1614699481403_828029.png","style_bigPic":"","sys_moduleType":2,"sys_z":60,"nFlag":1,"sys_w":60,"sys_y":590,"sys_x":307,"sys_h":60,"nPageType":0,"style_eventType":"2"},{"style_textSize":13,"style_textAlign":1,"sys_moduleType":3,"sys_z":61,"sys_w":110,"sys_y":0,"style_textAlpha":"100","sys_x":265,"style_textColor":"FFFFFF","style_galleryTextAlpha":"100","data_text":"225个/17个/29个","style_textBold":0,"sys_h":25},{"nPageId":"","data_pic":"1614698216310_934957.png","style_bigPic":"","sys_moduleType":2,"sys_z":62,"nFlag":0,"sys_w":25,"sys_y":625,"sys_x":42,"sys_h":25,"nPageType":0,"style_eventType":"2"},{"nPageId":"","data_pic":"1614618343071_1001740.png","style_bigPic":"","sys_moduleType":2,"sys_z":63,"nFlag":0,"sys_w":25,"sys_y":265,"sys_x":342,"sys_h":25,"nPageType":0,"style_eventType":"2"},{"style_textSize":13,"style_textAlign":1,"sys_moduleType":3,"sys_z":64,"sys_w":110,"sys_y":25,"style_textAlpha":"100","sys_x":265,"style_textColor":"FFFFFF","style_galleryTextAlpha":"100","data_text":"271个","style_textBold":0,"sys_h":25},{"nPageId":"","data_pic":"1614265676128_1092672.png","style_bigPic":"","sys_moduleType":2,"sys_z":65,"nFlag":0,"sys_w":25,"sys_y":265,"sys_x":127,"sys_h":25,"nPageType":0,"style_eventType":"2"},{"nPageId":"","data_pic":"1614698543774_611786.png","style_bigPic":"","sys_moduleType":2,"sys_z":66,"nFlag":0,"sys_w":25,"sys_y":265,"sys_x":247,"sys_h":25,"nPageType":0,"style_eventType":"2"},{"nPageId":"","data_pic":"1614265839095_769610.png","style_bigPic":"","sys_moduleType":2,"sys_z":67,"nFlag":0,"sys_w":25,"sys_y":565,"sys_x":222,"sys_h":25,"nPageType":0,"style_eventType":"2"},{"nPageId":"","data_pic":"1614618485537_988260.png","style_bigPic":"","sys_moduleType":2,"sys_z":68,"nFlag":0,"sys_w":25,"sys_y":145,"sys_x":162,"sys_h":25,"nPageType":0,"style_eventType":"2"},{"nPageId":"","data_pic":"1614699465567_178241.png","style_bigPic":"","sys_moduleType":2,"sys_z":69,"nFlag":0,"sys_w":25,"sys_y":565,"sys_x":127,"sys_h":25,"nPageType":0,"style_eventType":"2"},{"style_textSize":13,"style_textAlign":1,"sys_moduleType":3,"sys_z":70,"sys_w":120,"sys_y":650,"style_textAlpha":"100","sys_x":127,"style_textColor":"FFFFFF","style_galleryTextAlpha":"100","data_text":"1/5","style_textBold":0,"sys_h":30},{"nPageId":"8ebf3911-7a79-4b1a-af62-c50592d837e2","data_pic":"1616156272516_599012.png","style_bigPic":"","sys_moduleType":2,"sys_z":71,"nFlag":1,"sys_w":30,"sys_y":650,"sys_x":217,"sys_h":30,"nPageType":0,"style_eventType":"2"},{"nPageId":"8a335cb6-bdee-4a5d-b70d-0036ab9ca13b","data_pic":"1616919931480_361961.png","style_bigPic":"","sys_moduleType":2,"sys_z":72,"nFlag":1,"sys_w":60,"sys_y":470,"sys_x":127,"sys_h":60,"nPageType":0,"style_eventType":"2"},{"nPageId":"","data_pic":"1614698216310_934957.png","style_bigPic":"","sys_moduleType":2,"sys_z":73,"nFlag":0,"sys_w":25,"sys_y":565,"sys_x":342,"sys_h":25,"nPageType":0,"style_eventType":"2"},{"nPageId":"9ab1bfd3-0e13-4a5e-b90e-34a7f98baca1","data_pic":"1618063066758_612158.png","style_bigPic":"","sys_moduleType":2,"sys_z":74,"nFlag":1,"sys_w":60,"sys_y":470,"sys_x":67,"sys_h":60,"nPageType":0,"style_eventType":"2"},{"nPageId":"a3b24f78-07fc-487c-8801-241a08e80954","data_pic":"1622033289938_806815.png","style_bigPic":"","sys_moduleType":2,"sys_z":75,"nFlag":1,"sys_w":60,"sys_y":350,"sys_x":127,"sys_h":60,"nPageType":0,"style_eventType":"2"},{"nPageId":"f68908d3-d3b2-40b2-a092-e0cdbfbe562a","data_pic":"1616919834670_974064.png","style_bigPic":"","sys_moduleType":2,"sys_z":76,"nFlag":1,"sys_w":60,"sys_y":350,"sys_x":7,"sys_h":60,"nPageType":0,"style_eventType":"2"},{"nPageId":"e6277d19-4e4d-4111-8c1c-0017ce486df4","data_pic":"1623237518911_310431.png","style_bigPic":"","sys_moduleType":2,"sys_z":77,"nFlag":1,"sys_w":60,"sys_y":350,"sys_x":67,"sys_h":60,"nPageType":0,"style_eventType":"2"},{"nPageId":"","data_pic":"1614618363754_699326.png","style_bigPic":"","sys_moduleType":2,"sys_z":78,"nFlag":0,"sys_w":25,"sys_y":445,"sys_x":42,"sys_h":25,"nPageType":0,"style_eventType":"2"},{"nPageId":"fffe98b1-dcde-4923-9646-59c4b4259d9e","data_pic":"1635348400015_200111.png","style_bigPic":"","sys_moduleType":2,"sys_z":79,"nFlag":1,"sys_w":60,"sys_y":470,"sys_x":7,"sys_h":60,"nPageType":0,"style_eventType":"2"},{"nPageId":"b9de6bad-abca-4ca9-8123-5af99a03c086","data_pic":"1635348394023_474060.png","style_bigPic":"","sys_moduleType":2,"sys_z":80,"nFlag":1,"sys_w":60,"sys_y":410,"sys_x":247,"sys_h":60,"nPageType":0,"style_eventType":"2"},{"nPageId":"","data_pic":"1635348389557_757460.png","style_bigPic":"","sys_moduleType":2,"sys_z":81,"nFlag":0,"sys_w":25,"sys_y":505,"sys_x":42,"sys_h":25,"nPageType":0,"style_eventType":"2"},{"nPageId":"8fc40a41-d5d8-4a6b-a091-bab523f98223","data_pic":"1626791762855_334316.png","style_bigPic":"","sys_moduleType":2,"sys_z":82,"nFlag":1,"sys_w":60,"sys_y":350,"sys_x":187,"sys_h":60,"nPageType":0,"style_eventType":"2"},{"nPageId":"816796f0-9a92-4d54-b3af-dd16f5d0c525","data_pic":"1642520015114_471868.png","style_bigPic":"","sys_moduleType":2,"sys_z":83,"nFlag":1,"sys_w":60,"sys_y":410,"sys_x":307,"sys_h":60,"nPageType":0,"style_eventType":"2"},{"nPageId":"258f450c-0fa6-407a-9959-934328980c97","data_pic":"1635506139089_918261.png","style_bigPic":"","sys_moduleType":2,"sys_z":84,"nFlag":1,"sys_w":60,"sys_y":470,"sys_x":187,"sys_h":60,"nPageType":0,"style_eventType":"2"}],"style_tFlag":0,"style_tNavID":"","sys_pageID":"bef85e16-856c-4e2f-8303-52d00eade8e3","itemNew":"","data_password":"","style_bNavType":2001,"itemName":"","style_bFlag":0,"style_bNavID":"","style_bgType":2,"style_bgPic":"btn-28.jpg","style_bgColor":"FFFFFF","style_tNavType":1001}