{"data_pageName":"","style_bgAlpha":100,"data_shoppingFloat":"","item":[{"style_textSize":20,"style_textAlign":1,"sys_moduleType":3,"sys_z":0,"sys_w":160,"sys_y":0,"style_textAlpha":"100","sys_x":107,"style_textColor":"FFFFFF","style_galleryTextAlpha":"100","data_text":"属性暴龙机(三卡)","style_textBold":0,"sys_h":40},{"nPageId":null,"style_bgAlpha":100,"style_textSize":13,"style_textAlign":1,"sys_moduleType":1,"sys_z":1,"sys_w":100,"sys_y":5,"style_textAlpha":"100","sys_x":7,"nPageType":3,"style_textColor":"FFFFFF","nFlag":1,"style_galleryTextAlpha":"100","data_text":"上一页","style_bgType":1,"style_bgPic":"","style_textBold":0,"style_bgColor":"1DC6F1","sys_h":30},{"nPageId":"","data_pic":"1616937872012_341819.png","style_bigPic":"","sys_moduleType":2,"sys_z":2,"nFlag":0,"sys_w":50,"sys_y":60,"sys_x":162,"sys_h":50,"nPageType":0,"style_eventType":"2"},{"nPageId":"","style_bgAlpha":100,"style_textSize":13,"style_textAlign":1,"sys_moduleType":1,"sys_z":3,"sys_w":100,"sys_y":120,"style_textAlpha":"100","sys_x":0,"nPageType":0,"style_textColor":"FFFFFF","nFlag":0,"style_galleryTextAlpha":"100","data_text":"能力","style_bgType":1,"style_bgPic":"","style_textBold":0,"style_bgColor":"C0505D","sys_h":30},{"nPageId":"","style_bgAlpha":100,"style_textSize":13,"style_textAlign":1,"sys_moduleType":1,"sys_z":4,"sys_w":75,"sys_y":120,"style_textAlpha":"100","sys_x":100,"nPageType":0,"style_textColor":"FFFFFF","nFlag":0,"style_galleryTextAlpha":"100","data_text":"英文","style_bgType":1,"style_bgPic":"","style_textBold":0,"style_bgColor":"C0505D","sys_h":30},{"nPageId":"","style_bgAlpha":100,"style_textSize":13,"style_textAlign":1,"sys_moduleType":1,"sys_z":5,"sys_w":50,"sys_y":120,"style_textAlpha":"100","sys_x":175,"nPageType":0,"style_textColor":"FFFFFF","nFlag":0,"style_galleryTextAlpha":"100","data_text":"100%","style_bgType":1,"style_bgPic":"","style_textBold":0,"style_bgColor":"C0505D","sys_h":30},{"nPageId":"","style_bgAlpha":100,"style_textSize":13,"style_textAlign":1,"sys_moduleType":1,"sys_z":6,"sys_w":50,"sys_y":120,"style_textAlpha":"100","sys_x":225,"nPageType":0,"style_textColor":"FFFFFF","nFlag":0,"style_galleryTextAlpha":"100","data_text":"200%","style_bgType":1,"style_bgPic":"","style_textBold":0,"style_bgColor":"C0505D","sys_h":30},{"nPageId":"","style_bgAlpha":100,"style_textSize":13,"style_textAlign":1,"sys_moduleType":1,"sys_z":7,"sys_w":100,"sys_y":120,"style_textAlpha":"100","sys_x":275,"nPageType":0,"style_textColor":"FFFFFF","nFlag":0,"style_galleryTextAlpha":"100","data_text":"最大出现次数","style_bgType":1,"style_bgPic":"","style_textBold":0,"style_bgColor":"C0505D","sys_h":30},{"nPageId":"","style_bgAlpha":100,"style_textSize":13,"style_textAlign":1,"sys_moduleType":1,"sys_z":8,"sys_w":100,"sys_y":150,"style_textAlpha":"100","sys_x":0,"nPageType":0,"style_textColor":"000000","nFlag":0,"style_galleryTextAlpha":"100","data_text":"疫苗属性伤害","style_bgType":1,"style_bgPic":"","style_textBold":0,"style_bgColor":"FBD5B5","sys_h":30},{"nPageId":"","style_bgAlpha":100,"style_textSize":13,"style_textAlign":1,"sys_moduleType":1,"sys_z":9,"sys_w":100,"sys_y":180,"style_textAlpha":"100","sys_x":0,"nPageType":0,"style_textColor":"000000","nFlag":0,"style_galleryTextAlpha":"100","data_text":"病毒属性伤害","style_bgType":1,"style_bgPic":"","style_textBold":0,"style_bgColor":"FAC08F","sys_h":30},{"nPageId":"","style_bgAlpha":100,"style_textSize":13,"style_textAlign":1,"sys_moduleType":1,"sys_z":10,"sys_w":100,"sys_y":210,"style_textAlpha":"100","sys_x":0,"nPageType":0,"style_textColor":"000000","nFlag":0,"style_galleryTextAlpha":"100","data_text":"资料属性伤害","style_bgType":1,"style_bgPic":"","style_textBold":0,"style_bgColor":"FBD5B5","sys_h":30},{"nPageId":"","style_bgAlpha":100,"style_textSize":13,"style_textAlign":1,"sys_moduleType":1,"sys_z":11,"sys_w":100,"sys_y":240,"style_textAlpha":"100","sys_x":0,"nPageType":0,"style_textColor":"000000","nFlag":0,"style_galleryTextAlpha":"100","data_text":"不明属性伤害","style_bgType":1,"style_bgPic":"","style_textBold":0,"style_bgColor":"FAC08F","sys_h":30},{"nPageId":"","style_bgAlpha":100,"style_textSize":13,"style_textAlign":1,"sys_moduleType":1,"sys_z":12,"sys_w":100,"sys_y":270,"style_textAlpha":"100","sys_x":0,"nPageType":0,"style_textColor":"000000","nFlag":0,"style_galleryTextAlpha":"100","data_text":"火属性伤害","style_bgType":1,"style_bgPic":"","style_textBold":0,"style_bgColor":"FBD5B5","sys_h":30},{"nPageId":"","style_bgAlpha":100,"style_textSize":13,"style_textAlign":1,"sys_moduleType":1,"sys_z":13,"sys_w":100,"sys_y":300,"style_textAlpha":"100","sys_x":0,"nPageType":0,"style_textColor":"000000","nFlag":0,"style_galleryTextAlpha":"100","data_text":"风属性伤害","style_bgType":1,"style_bgPic":"","style_textBold":0,"style_bgColor":"FAC08F","sys_h":30},{"nPageId":"","style_bgAlpha":100,"style_textSize":13,"style_textAlign":1,"sys_moduleType":1,"sys_z":14,"sys_w":100,"sys_y":330,"style_textAlpha":"100","sys_x":0,"nPageType":0,"style_textColor":"000000","nFlag":0,"style_galleryTextAlpha":"100","data_text":"冰属性伤害","style_bgType":1,"style_bgPic":"","style_textBold":0,"style_bgColor":"FBD5B5","sys_h":30},{"nPageId":"","style_bgAlpha":100,"style_textSize":13,"style_textAlign":1,"sys_moduleType":1,"sys_z":15,"sys_w":100,"sys_y":360,"style_textAlpha":"100","sys_x":0,"nPageType":0,"style_textColor":"000000","nFlag":0,"style_galleryTextAlpha":"100","data_text":"木属性伤害","style_bgType":1,"style_bgPic":"","style_textBold":0,"style_bgColor":"FAC08F","sys_h":30},{"nPageId":"","style_bgAlpha":100,"style_textSize":13,"style_textAlign":1,"sys_moduleType":1,"sys_z":16,"sys_w":100,"sys_y":390,"style_textAlpha":"100","sys_x":0,"nPageType":0,"style_textColor":"000000","nFlag":0,"style_galleryTextAlpha":"100","data_text":"土属性伤害","style_bgType":1,"style_bgPic":"","style_textBold":0,"style_bgColor":"FBD5B5","sys_h":30},{"nPageId":"","style_bgAlpha":100,"style_textSize":13,"style_textAlign":1,"sys_moduleType":1,"sys_z":17,"sys_w":100,"sys_y":420,"style_textAlpha":"100","sys_x":0,"nPageType":0,"style_textColor":"000000","nFlag":0,"style_galleryTextAlpha":"100","data_text":"光属性伤害","style_bgType":1,"style_bgPic":"","style_textBold":0,"style_bgColor":"FAC08F","sys_h":30},{"nPageId":"","style_bgAlpha":100,"style_textSize":13,"style_textAlign":1,"sys_moduleType":1,"sys_z":18,"sys_w":100,"sys_y":450,"style_textAlpha":"100","sys_x":0,"nPageType":0,"style_textColor":"000000","nFlag":0,"style_galleryTextAlpha":"100","data_text":"雷属性伤害","style_bgType":1,"style_bgPic":"","style_textBold":0,"style_bgColor":"FBD5B5","sys_h":30},{"nPageId":"","style_bgAlpha":100,"style_textSize":13,"style_textAlign":1,"sys_moduleType":1,"sys_z":19,"sys_w":100,"sys_y":480,"style_textAlpha":"100","sys_x":0,"nPageType":0,"style_textColor":"000000","nFlag":0,"style_galleryTextAlpha":"100","data_text":"暗属性伤害","style_bgType":1,"style_bgPic":"","style_textBold":0,"style_bgColor":"FAC08F","sys_h":30},{"nPageId":"","style_bgAlpha":100,"style_textSize":13,"style_textAlign":1,"sys_moduleType":1,"sys_z":20,"sys_w":100,"sys_y":510,"style_textAlpha":"100","sys_x":0,"nPageType":0,"style_textColor":"000000","nFlag":0,"style_galleryTextAlpha":"100","data_text":"水属性伤害","style_bgType":1,"style_bgPic":"","style_textBold":0,"style_bgColor":"FBD5B5","sys_h":30},{"nPageId":"","style_bgAlpha":100,"style_textSize":13,"style_textAlign":1,"sys_moduleType":1,"sys_z":21,"sys_w":100,"sys_y":540,"style_textAlpha":"100","sys_x":0,"nPageType":0,"style_textColor":"000000","nFlag":0,"style_galleryTextAlpha":"100","data_text":"钢属性伤害","style_bgType":1,"style_bgPic":"","style_textBold":0,"style_bgColor":"FAC08F","sys_h":30},{"nPageId":"","style_bgAlpha":100,"style_textSize":13,"style_textAlign":1,"sys_moduleType":1,"sys_z":22,"sys_w":75,"sys_y":150,"style_textAlpha":"100","sys_x":100,"nPageType":0,"style_textColor":"000000","nFlag":0,"style_galleryTextAlpha":"100","data_text":"Va ATT","style_bgType":1,"style_bgPic":"","style_textBold":0,"style_bgColor":"FAC08F","sys_h":30},{"nPageId":"","style_bgAlpha":100,"style_textSize":13,"style_textAlign":1,"sys_moduleType":1,"sys_z":23,"sys_w":75,"sys_y":180,"style_textAlpha":"100","sys_x":100,"nPageType":0,"style_textColor":"000000","nFlag":0,"style_galleryTextAlpha":"100","data_text":"Vi ATT","style_bgType":1,"style_bgPic":"","style_textBold":0,"style_bgColor":"FBD5B5","sys_h":30},{"nPageId":"","style_bgAlpha":100,"style_textSize":13,"style_textAlign":1,"sys_moduleType":1,"sys_z":24,"sys_w":75,"sys_y":210,"style_textAlpha":"100","sys_x":100,"nPageType":0,"style_textColor":"000000","nFlag":0,"style_galleryTextAlpha":"100","data_text":"Da ATT","style_bgType":1,"style_bgPic":"","style_textBold":0,"style_bgColor":"FAC08F","sys_h":30},{"nPageId":"","style_bgAlpha":100,"style_textSize":13,"style_textAlign":1,"sys_moduleType":1,"sys_z":25,"sys_w":75,"sys_y":240,"style_textAlpha":"100","sys_x":100,"nPageType":0,"style_textColor":"000000","nFlag":0,"style_galleryTextAlpha":"100","data_text":"Un ATT","style_bgType":1,"style_bgPic":"","style_textBold":0,"style_bgColor":"FBD5B5","sys_h":30},{"nPageId":"","style_bgAlpha":100,"style_textSize":13,"style_textAlign":1,"sys_moduleType":1,"sys_z":26,"sys_w":75,"sys_y":270,"style_textAlpha":"100","sys_x":100,"nPageType":0,"style_textColor":"000000","nFlag":0,"style_galleryTextAlpha":"100","data_text":"Fire ATT","style_bgType":1,"style_bgPic":"","style_textBold":0,"style_bgColor":"FAC08F","sys_h":30},{"nPageId":"","style_bgAlpha":100,"style_textSize":13,"style_textAlign":1,"sys_moduleType":1,"sys_z":27,"sys_w":75,"sys_y":420,"style_textAlpha":"100","sys_x":100,"nPageType":0,"style_textColor":"000000","nFlag":0,"style_galleryTextAlpha":"100","data_text":"Light ATT","style_bgType":1,"style_bgPic":"","style_textBold":0,"style_bgColor":"FBD5B5","sys_h":30},{"nPageId":"","style_bgAlpha":100,"style_textSize":13,"style_textAlign":1,"sys_moduleType":1,"sys_z":28,"sys_w":75,"sys_y":300,"style_textAlpha":"100","sys_x":100,"nPageType":0,"style_textColor":"000000","nFlag":0,"style_galleryTextAlpha":"100","data_text":"Wind ATT","style_bgType":1,"style_bgPic":"","style_textBold":0,"style_bgColor":"FBD5B5","sys_h":30},{"nPageId":"","style_bgAlpha":100,"style_textSize":13,"style_textAlign":1,"sys_moduleType":1,"sys_z":29,"sys_w":75,"sys_y":330,"style_textAlpha":"100","sys_x":100,"nPageType":0,"style_textColor":"000000","nFlag":0,"style_galleryTextAlpha":"100","data_text":"Ice ATT","style_bgType":1,"style_bgPic":"","style_textBold":0,"style_bgColor":"FAC08F","sys_h":30},{"nPageId":"","style_bgAlpha":100,"style_textSize":13,"style_textAlign":1,"sys_moduleType":1,"sys_z":30,"sys_w":75,"sys_y":360,"style_textAlpha":"100","sys_x":100,"nPageType":0,"style_textColor":"000000","nFlag":0,"style_galleryTextAlpha":"100","data_text":"Wood ATT","style_bgType":1,"style_bgPic":"","style_textBold":0,"style_bgColor":"FBD5B5","sys_h":30},{"nPageId":"","style_bgAlpha":100,"style_textSize":12,"style_textAlign":1,"sys_moduleType":1,"sys_z":31,"sys_w":75,"sys_y":450,"style_textAlpha":"100","sys_x":100,"nPageType":0,"style_textColor":"000000","nFlag":0,"style_galleryTextAlpha":"100","data_text":"Thunder ATT","style_bgType":1,"style_bgPic":"","style_textBold":0,"style_bgColor":"FAC08F","sys_h":30},{"nPageId":"","style_bgAlpha":100,"style_textSize":13,"style_textAlign":1,"sys_moduleType":1,"sys_z":32,"sys_w":75,"sys_y":480,"style_textAlpha":"100","sys_x":100,"nPageType":0,"style_textColor":"000000","nFlag":0,"style_galleryTextAlpha":"100","data_text":"Dark ATT","style_bgType":1,"style_bgPic":"","style_textBold":0,"style_bgColor":"FBD5B5","sys_h":30},{"nPageId":"","style_bgAlpha":100,"style_textSize":13,"style_textAlign":1,"sys_moduleType":1,"sys_z":33,"sys_w":75,"sys_y":510,"style_textAlpha":"100","sys_x":100,"nPageType":0,"style_textColor":"000000","nFlag":0,"style_galleryTextAlpha":"100","data_text":"Water ATT","style_bgType":1,"style_bgPic":"","style_textBold":0,"style_bgColor":"FAC08F","sys_h":30},{"nPageId":"","style_bgAlpha":100,"style_textSize":13,"style_textAlign":1,"sys_moduleType":1,"sys_z":34,"sys_w":75,"sys_y":390,"style_textAlpha":"100","sys_x":100,"nPageType":0,"style_textColor":"000000","nFlag":0,"style_galleryTextAlpha":"100","data_text":"Land ATT","style_bgType":1,"style_bgPic":"","style_textBold":0,"style_bgColor":"FAC08F","sys_h":30},{"nPageId":"","style_bgAlpha":100,"style_textSize":13,"style_textAlign":1,"sys_moduleType":1,"sys_z":35,"sys_w":75,"sys_y":540,"style_textAlpha":"100","sys_x":100,"nPageType":0,"style_textColor":"000000","nFlag":0,"style_galleryTextAlpha":"100","data_text":"Steel ATT","style_bgType":1,"style_bgPic":"","style_textBold":0,"style_bgColor":"FBD5B5","sys_h":30},{"nPageId":"","style_bgAlpha":100,"style_textSize":13,"style_textAlign":1,"sys_moduleType":1,"sys_z":36,"sys_w":50,"sys_y":150,"style_textAlpha":"100","sys_x":175,"nPageType":0,"style_textColor":"000000","nFlag":0,"style_galleryTextAlpha":"100","data_text":"7.00%","style_bgType":1,"style_bgPic":"","style_textBold":0,"style_bgColor":"FBD5B5","sys_h":30},{"nPageId":"","style_bgAlpha":100,"style_textSize":13,"style_textAlign":1,"sys_moduleType":1,"sys_z":37,"sys_w":50,"sys_y":210,"style_textAlpha":"100","sys_x":175,"nPageType":0,"style_textColor":"000000","nFlag":0,"style_galleryTextAlpha":"100","data_text":"7.00%","style_bgType":1,"style_bgPic":"","style_textBold":0,"style_bgColor":"FBD5B5","sys_h":30},{"nPageId":"","style_bgAlpha":100,"style_textSize":13,"style_textAlign":1,"sys_moduleType":1,"sys_z":38,"sys_w":50,"sys_y":270,"style_textAlpha":"100","sys_x":175,"nPageType":0,"style_textColor":"000000","nFlag":0,"style_galleryTextAlpha":"100","data_text":"10.00%","style_bgType":1,"style_bgPic":"","style_textBold":0,"style_bgColor":"FBD5B5","sys_h":30},{"nPageId":"","style_bgAlpha":100,"style_textSize":13,"style_textAlign":1,"sys_moduleType":1,"sys_z":39,"sys_w":50,"sys_y":180,"style_textAlpha":"100","sys_x":175,"nPageType":0,"style_textColor":"000000","nFlag":0,"style_galleryTextAlpha":"100","data_text":"7.00%","style_bgType":1,"style_bgPic":"","style_textBold":0,"style_bgColor":"FAC08F","sys_h":30},{"nPageId":"","style_bgAlpha":100,"style_textSize":13,"style_textAlign":1,"sys_moduleType":1,"sys_z":40,"sys_w":50,"sys_y":240,"style_textAlpha":"100","sys_x":175,"nPageType":0,"style_textColor":"000000","nFlag":0,"style_galleryTextAlpha":"100","data_text":"5.00%","style_bgType":1,"style_bgPic":"","style_textBold":0,"style_bgColor":"FAC08F","sys_h":30},{"nPageId":"","style_bgAlpha":100,"style_textSize":13,"style_textAlign":1,"sys_moduleType":1,"sys_z":41,"sys_w":50,"sys_y":300,"style_textAlpha":"100","sys_x":175,"nPageType":0,"style_textColor":"000000","nFlag":0,"style_galleryTextAlpha":"100","data_text":"10.00%","style_bgType":1,"style_bgPic":"","style_textBold":0,"style_bgColor":"FAC08F","sys_h":30},{"nPageId":"","style_bgAlpha":100,"style_textSize":13,"style_textAlign":1,"sys_moduleType":1,"sys_z":42,"sys_w":50,"sys_y":150,"style_textAlpha":"100","sys_x":225,"nPageType":0,"style_textColor":"000000","nFlag":0,"style_galleryTextAlpha":"100","data_text":"14.00%","style_bgType":1,"style_bgPic":"","style_textBold":0,"style_bgColor":"FAC08F","sys_h":30},{"nPageId":"","style_bgAlpha":100,"style_textSize":13,"style_textAlign":1,"sys_moduleType":1,"sys_z":43,"sys_w":50,"sys_y":210,"style_textAlpha":"100","sys_x":225,"nPageType":0,"style_textColor":"000000","nFlag":0,"style_galleryTextAlpha":"100","data_text":"14.00%","style_bgType":1,"style_bgPic":"","style_textBold":0,"style_bgColor":"FAC08F","sys_h":30},{"nPageId":"","style_bgAlpha":100,"style_textSize":13,"style_textAlign":1,"sys_moduleType":1,"sys_z":44,"sys_w":50,"sys_y":270,"style_textAlpha":"100","sys_x":225,"nPageType":0,"style_textColor":"000000","nFlag":0,"style_galleryTextAlpha":"100","data_text":"20.00%","style_bgType":1,"style_bgPic":"","style_textBold":0,"style_bgColor":"FAC08F","sys_h":30},{"nPageId":"","style_bgAlpha":100,"style_textSize":13,"style_textAlign":1,"sys_moduleType":1,"sys_z":45,"sys_w":50,"sys_y":180,"style_textAlpha":"100","sys_x":225,"nPageType":0,"style_textColor":"000000","nFlag":0,"style_galleryTextAlpha":"100","data_text":"14.00%","style_bgType":1,"style_bgPic":"","style_textBold":0,"style_bgColor":"FBD5B5","sys_h":30},{"nPageId":"","style_bgAlpha":100,"style_textSize":13,"style_textAlign":1,"sys_moduleType":1,"sys_z":46,"sys_w":50,"sys_y":240,"style_textAlpha":"100","sys_x":225,"nPageType":0,"style_textColor":"000000","nFlag":0,"style_galleryTextAlpha":"100","data_text":"10.00%","style_bgType":1,"style_bgPic":"","style_textBold":0,"style_bgColor":"FBD5B5","sys_h":30},{"nPageId":"","style_bgAlpha":100,"style_textSize":13,"style_textAlign":1,"sys_moduleType":1,"sys_z":47,"sys_w":50,"sys_y":300,"style_textAlpha":"100","sys_x":225,"nPageType":0,"style_textColor":"000000","nFlag":0,"style_galleryTextAlpha":"100","data_text":"20.00%","style_bgType":1,"style_bgPic":"","style_textBold":0,"style_bgColor":"FBD5B5","sys_h":30},{"nPageId":"","style_bgAlpha":100,"style_textSize":13,"style_textAlign":1,"sys_moduleType":1,"sys_z":48,"sys_w":100,"sys_y":150,"style_textAlpha":"100","sys_x":275,"nPageType":0,"style_textColor":"000000","nFlag":0,"style_galleryTextAlpha":"100","data_text":"1","style_bgType":1,"style_bgPic":"","style_textBold":0,"style_bgColor":"FBD5B5","sys_h":30},{"nPageId":"","style_bgAlpha":100,"style_textSize":13,"style_textAlign":1,"sys_moduleType":1,"sys_z":49,"sys_w":100,"sys_y":180,"style_textAlpha":"100","sys_x":275,"nPageType":0,"style_textColor":"000000","nFlag":0,"style_galleryTextAlpha":"100","data_text":"1","style_bgType":1,"style_bgPic":"","style_textBold":0,"style_bgColor":"FAC08F","sys_h":30},{"nPageId":"","style_bgAlpha":100,"style_textSize":13,"style_textAlign":1,"sys_moduleType":1,"sys_z":50,"sys_w":100,"sys_y":210,"style_textAlpha":"100","sys_x":275,"nPageType":0,"style_textColor":"000000","nFlag":0,"style_galleryTextAlpha":"100","data_text":"1","style_bgType":1,"style_bgPic":"","style_textBold":0,"style_bgColor":"FBD5B5","sys_h":30},{"nPageId":"","style_bgAlpha":100,"style_textSize":13,"style_textAlign":1,"sys_moduleType":1,"sys_z":51,"sys_w":100,"sys_y":270,"style_textAlpha":"100","sys_x":275,"nPageType":0,"style_textColor":"000000","nFlag":0,"style_galleryTextAlpha":"100","data_text":"1","style_bgType":1,"style_bgPic":"","style_textBold":0,"style_bgColor":"FBD5B5","sys_h":30},{"nPageId":"","style_bgAlpha":100,"style_textSize":13,"style_textAlign":1,"sys_moduleType":1,"sys_z":52,"sys_w":100,"sys_y":330,"style_textAlpha":"100","sys_x":275,"nPageType":0,"style_textColor":"000000","nFlag":0,"style_galleryTextAlpha":"100","data_text":"1","style_bgType":1,"style_bgPic":"","style_textBold":0,"style_bgColor":"FBD5B5","sys_h":30},{"nPageId":"","style_bgAlpha":100,"style_textSize":13,"style_textAlign":1,"sys_moduleType":1,"sys_z":53,"sys_w":100,"sys_y":390,"style_textAlpha":"100","sys_x":275,"nPageType":0,"style_textColor":"000000","nFlag":0,"style_galleryTextAlpha":"100","data_text":"1","style_bgType":1,"style_bgPic":"","style_textBold":0,"style_bgColor":"FBD5B5","sys_h":30},{"nPageId":"","style_bgAlpha":100,"style_textSize":13,"style_textAlign":1,"sys_moduleType":1,"sys_z":54,"sys_w":100,"sys_y":450,"style_textAlpha":"100","sys_x":275,"nPageType":0,"style_textColor":"000000","nFlag":0,"style_galleryTextAlpha":"100","data_text":"1","style_bgType":1,"style_bgPic":"","style_textBold":0,"style_bgColor":"FBD5B5","sys_h":30},{"nPageId":"","style_bgAlpha":100,"style_textSize":13,"style_textAlign":1,"sys_moduleType":1,"sys_z":55,"sys_w":100,"sys_y":510,"style_textAlpha":"100","sys_x":275,"nPageType":0,"style_textColor":"000000","nFlag":0,"style_galleryTextAlpha":"100","data_text":"1","style_bgType":1,"style_bgPic":"","style_textBold":0,"style_bgColor":"FBD5B5","sys_h":30},{"nPageId":"","style_bgAlpha":100,"style_textSize":13,"style_textAlign":1,"sys_moduleType":1,"sys_z":56,"sys_w":100,"sys_y":240,"style_textAlpha":"100","sys_x":275,"nPageType":0,"style_textColor":"000000","nFlag":0,"style_galleryTextAlpha":"100","data_text":"1","style_bgType":1,"style_bgPic":"","style_textBold":0,"style_bgColor":"FAC08F","sys_h":30},{"nPageId":"","style_bgAlpha":100,"style_textSize":13,"style_textAlign":1,"sys_moduleType":1,"sys_z":57,"sys_w":100,"sys_y":300,"style_textAlpha":"100","sys_x":275,"nPageType":0,"style_textColor":"000000","nFlag":0,"style_galleryTextAlpha":"100","data_text":"1","style_bgType":1,"style_bgPic":"","style_textBold":0,"style_bgColor":"FAC08F","sys_h":30},{"nPageId":"","style_bgAlpha":100,"style_textSize":13,"style_textAlign":1,"sys_moduleType":1,"sys_z":58,"sys_w":100,"sys_y":360,"style_textAlpha":"100","sys_x":275,"nPageType":0,"style_textColor":"000000","nFlag":0,"style_galleryTextAlpha":"100","data_text":"1","style_bgType":1,"style_bgPic":"","style_textBold":0,"style_bgColor":"FAC08F","sys_h":30},{"nPageId":"","style_bgAlpha":100,"style_textSize":13,"style_textAlign":1,"sys_moduleType":1,"sys_z":59,"sys_w":100,"sys_y":420,"style_textAlpha":"100","sys_x":275,"nPageType":0,"style_textColor":"000000","nFlag":0,"style_galleryTextAlpha":"100","data_text":"1","style_bgType":1,"style_bgPic":"","style_textBold":0,"style_bgColor":"FAC08F","sys_h":30},{"nPageId":"","style_bgAlpha":100,"style_textSize":13,"style_textAlign":1,"sys_moduleType":1,"sys_z":60,"sys_w":100,"sys_y":480,"style_textAlpha":"100","sys_x":275,"nPageType":0,"style_textColor":"000000","nFlag":0,"style_galleryTextAlpha":"100","data_text":"1","style_bgType":1,"style_bgPic":"","style_textBold":0,"style_bgColor":"FAC08F","sys_h":30},{"nPageId":"","style_bgAlpha":100,"style_textSize":13,"style_textAlign":1,"sys_moduleType":1,"sys_z":61,"sys_w":100,"sys_y":540,"style_textAlpha":"100","sys_x":275,"nPageType":0,"style_textColor":"000000","nFlag":0,"style_galleryTextAlpha":"100","data_text":"1","style_bgType":1,"style_bgPic":"","style_textBold":0,"style_bgColor":"FAC08F","sys_h":30},{"style_bgAlpha":100,"style_textSize":12,"style_textAlign":0,"sys_moduleType":4,"sys_z":62,"sys_w":375,"sys_y":570,"style_textAlpha":"100","sys_x":0,"style_textColor":"000000","style_galleryTextAlpha":"100","data_text":"暴龙机的单项非满值。暴龙机的属性伤害不考虑克制、不考虑技能属性，只要宠物属性符合就打什么都加技能伤害，和攻击ic/技能称号类似，不加普攻","style_bgType":1,"style_bgPic":"","style_textBold":0,"style_bgColor":"FFFFFF","sys_h":60},{"nPageId":"","style_bgAlpha":100,"style_textSize":13,"style_textAlign":1,"sys_moduleType":1,"sys_z":63,"sys_w":50,"sys_y":360,"style_textAlpha":"100","sys_x":175,"nPageType":0,"style_textColor":"000000","nFlag":0,"style_galleryTextAlpha":"100","data_text":"10.00%","style_bgType":1,"style_bgPic":"","style_textBold":0,"style_bgColor":"FAC08F","sys_h":30},{"nPageId":"","style_bgAlpha":100,"style_textSize":13,"style_textAlign":1,"sys_moduleType":1,"sys_z":64,"sys_w":50,"sys_y":360,"style_textAlpha":"100","sys_x":225,"nPageType":0,"style_textColor":"000000","nFlag":0,"style_galleryTextAlpha":"100","data_text":"20.00%","style_bgType":1,"style_bgPic":"","style_textBold":0,"style_bgColor":"FBD5B5","sys_h":30},{"nPageId":"","style_bgAlpha":100,"style_textSize":13,"style_textAlign":1,"sys_moduleType":1,"sys_z":65,"sys_w":50,"sys_y":420,"style_textAlpha":"100","sys_x":175,"nPageType":0,"style_textColor":"000000","nFlag":0,"style_galleryTextAlpha":"100","data_text":"10.00%","style_bgType":1,"style_bgPic":"","style_textBold":0,"style_bgColor":"FAC08F","sys_h":30},{"nPageId":"","style_bgAlpha":100,"style_textSize":13,"style_textAlign":1,"sys_moduleType":1,"sys_z":66,"sys_w":50,"sys_y":420,"style_textAlpha":"100","sys_x":225,"nPageType":0,"style_textColor":"000000","nFlag":0,"style_galleryTextAlpha":"100","data_text":"20.00%","style_bgType":1,"style_bgPic":"","style_textBold":0,"style_bgColor":"FBD5B5","sys_h":30},{"nPageId":"","style_bgAlpha":100,"style_textSize":13,"style_textAlign":1,"sys_moduleType":1,"sys_z":67,"sys_w":50,"sys_y":480,"style_textAlpha":"100","sys_x":175,"nPageType":0,"style_textColor":"000000","nFlag":0,"style_galleryTextAlpha":"100","data_text":"10.00%","style_bgType":1,"style_bgPic":"","style_textBold":0,"style_bgColor":"FAC08F","sys_h":30},{"nPageId":"","style_bgAlpha":100,"style_textSize":13,"style_textAlign":1,"sys_moduleType":1,"sys_z":68,"sys_w":50,"sys_y":480,"style_textAlpha":"100","sys_x":225,"nPageType":0,"style_textColor":"000000","nFlag":0,"style_galleryTextAlpha":"100","data_text":"20.00%","style_bgType":1,"style_bgPic":"","style_textBold":0,"style_bgColor":"FBD5B5","sys_h":30},{"nPageId":"","style_bgAlpha":100,"style_textSize":13,"style_textAlign":1,"sys_moduleType":1,"sys_z":69,"sys_w":50,"sys_y":540,"style_textAlpha":"100","sys_x":175,"nPageType":0,"style_textColor":"000000","nFlag":0,"style_galleryTextAlpha":"100","data_text":"10.00%","style_bgType":1,"style_bgPic":"","style_textBold":0,"style_bgColor":"FAC08F","sys_h":30},{"nPageId":"","style_bgAlpha":100,"style_textSize":13,"style_textAlign":1,"sys_moduleType":1,"sys_z":70,"sys_w":50,"sys_y":540,"style_textAlpha":"100","sys_x":225,"nPageType":0,"style_textColor":"000000","nFlag":0,"style_galleryTextAlpha":"100","data_text":"20.00%","style_bgType":1,"style_bgPic":"","style_textBold":0,"style_bgColor":"FBD5B5","sys_h":30},{"nPageId":"","style_bgAlpha":100,"style_textSize":13,"style_textAlign":1,"sys_moduleType":1,"sys_z":71,"sys_w":50,"sys_y":330,"style_textAlpha":"100","sys_x":175,"nPageType":0,"style_textColor":"000000","nFlag":0,"style_galleryTextAlpha":"100","data_text":"10.00%","style_bgType":1,"style_bgPic":"","style_textBold":0,"style_bgColor":"FBD5B5","sys_h":30},{"nPageId":"","style_bgAlpha":100,"style_textSize":13,"style_textAlign":1,"sys_moduleType":1,"sys_z":72,"sys_w":50,"sys_y":330,"style_textAlpha":"100","sys_x":225,"nPageType":0,"style_textColor":"000000","nFlag":0,"style_galleryTextAlpha":"100","data_text":"20.00%","style_bgType":1,"style_bgPic":"","style_textBold":0,"style_bgColor":"FAC08F","sys_h":30},{"nPageId":"","style_bgAlpha":100,"style_textSize":13,"style_textAlign":1,"sys_moduleType":1,"sys_z":73,"sys_w":50,"sys_y":390,"style_textAlpha":"100","sys_x":175,"nPageType":0,"style_textColor":"000000","nFlag":0,"style_galleryTextAlpha":"100","data_text":"10.00%","style_bgType":1,"style_bgPic":"","style_textBold":0,"style_bgColor":"FBD5B5","sys_h":30},{"nPageId":"","style_bgAlpha":100,"style_textSize":13,"style_textAlign":1,"sys_moduleType":1,"sys_z":74,"sys_w":50,"sys_y":390,"style_textAlpha":"100","sys_x":225,"nPageType":0,"style_textColor":"000000","nFlag":0,"style_galleryTextAlpha":"100","data_text":"20.00%","style_bgType":1,"style_bgPic":"","style_textBold":0,"style_bgColor":"FAC08F","sys_h":30},{"nPageId":"","style_bgAlpha":100,"style_textSize":13,"style_textAlign":1,"sys_moduleType":1,"sys_z":75,"sys_w":50,"sys_y":450,"style_textAlpha":"100","sys_x":175,"nPageType":0,"style_textColor":"000000","nFlag":0,"style_galleryTextAlpha":"100","data_text":"10.00%","style_bgType":1,"style_bgPic":"","style_textBold":0,"style_bgColor":"FBD5B5","sys_h":30},{"nPageId":"","style_bgAlpha":100,"style_textSize":13,"style_textAlign":1,"sys_moduleType":1,"sys_z":76,"sys_w":50,"sys_y":450,"style_textAlpha":"100","sys_x":225,"nPageType":0,"style_textColor":"000000","nFlag":0,"style_galleryTextAlpha":"100","data_text":"20.00%","style_bgType":1,"style_bgPic":"","style_textBold":0,"style_bgColor":"FAC08F","sys_h":30},{"nPageId":"","style_bgAlpha":100,"style_textSize":13,"style_textAlign":1,"sys_moduleType":1,"sys_z":77,"sys_w":50,"sys_y":510,"style_textAlpha":"100","sys_x":175,"nPageType":0,"style_textColor":"000000","nFlag":0,"style_galleryTextAlpha":"100","data_text":"10.00%","style_bgType":1,"style_bgPic":"","style_textBold":0,"style_bgColor":"FBD5B5","sys_h":30},{"nPageId":"","style_bgAlpha":100,"style_textSize":13,"style_textAlign":1,"sys_moduleType":1,"sys_z":78,"sys_w":50,"sys_y":510,"style_textAlpha":"100","sys_x":225,"nPageType":0,"style_textColor":"000000","nFlag":0,"style_galleryTextAlpha":"100","data_text":"20.00%","style_bgType":1,"style_bgPic":"","style_textBold":0,"style_bgColor":"FAC08F","sys_h":30},{"style_bgAlpha":100,"style_textSize":12,"style_textAlign":0,"sys_moduleType":4,"sys_z":79,"sys_w":375,"sys_y":630,"style_textAlpha":"100","sys_x":0,"style_textColor":"FF0000","style_galleryTextAlpha":"100","data_text":"*翻译差异：土属性=地属性，钢属性=钢铁属性","style_bgType":1,"style_bgPic":"","style_textBold":0,"style_bgColor":"FFFFFF","sys_h":20},{"style_bgAlpha":100,"style_textSize":12,"style_textAlign":0,"sys_moduleType":4,"sys_z":80,"sys_w":100,"sys_y":0,"style_textAlpha":"100","sys_x":275,"style_textColor":"000000","style_galleryTextAlpha":"100","data_text":"以下最大值是可能数值，非官方数据，不一定对","style_bgType":1,"style_bgPic":"","style_textBold":0,"style_bgColor":"FDF700","sys_h":60}],"style_tFlag":0,"style_tNavID":"","sys_pageID":"01951152-e849-48b1-a2a5-19fc5061ad44","itemNew":"","data_password":"","style_bNavType":2001,"itemName":"","style_bFlag":0,"style_bNavID":"","style_bgType":2,"style_bgPic":"btn-28.jpg","style_bgColor":"FFFFFF","style_tNavType":1001}