{"data_pageName":"","style_bgAlpha":100,"data_shoppingFloat":"","item":[{"style_textSize":15,"style_textAlign":1,"sys_moduleType":3,"sys_z":0,"sys_w":200,"sys_y":0,"style_textAlpha":"100","sys_x":88,"style_textColor":"FFFFFF","style_galleryTextAlpha":"100","data_text":"黑大耳兽","style_textBold":0,"sys_h":25},{"nPageId":null,"data_pic":"btn-80.png","style_bigPic":"","sys_moduleType":2,"sys_z":1,"nFlag":1,"sys_w":30,"sys_y":5,"sys_x":8,"sys_h":30,"nPageType":2,"style_eventType":"2"},{"nPageId":"","style_bgAlpha":100,"style_textSize":13,"style_textAlign":1,"sys_moduleType":1,"sys_z":2,"sys_w":100,"sys_y":50,"style_textAlpha":"100","sys_x":275,"nPageType":0,"style_textColor":"FFFFFF","nFlag":0,"style_galleryTextAlpha":"100","data_text":"成长期","style_bgType":1,"style_bgPic":"","style_textBold":0,"style_bgColor":"1DC6F1","sys_h":30},{"nPageId":"","style_bgAlpha":100,"style_textSize":13,"style_textAlign":1,"sys_moduleType":1,"sys_z":3,"sys_w":87,"sys_y":50,"style_textAlpha":"100","sys_x":188,"nPageType":0,"style_textColor":"FFFFFF","nFlag":0,"style_galleryTextAlpha":"100","data_text":"阶段","style_bgType":1,"style_bgPic":"","style_textBold":0,"style_bgColor":"C0505D","sys_h":30},{"nPageId":"","style_bgAlpha":100,"style_textSize":13,"style_textAlign":1,"sys_moduleType":1,"sys_z":4,"sys_w":87,"sys_y":80,"style_textAlpha":"100","sys_x":188,"nPageType":0,"style_textColor":"FFFFFF","nFlag":0,"style_galleryTextAlpha":"100","data_text":"属性","style_bgType":1,"style_bgPic":"","style_textBold":0,"style_bgColor":"C0505D","sys_h":30},{"nPageId":"","style_bgAlpha":100,"style_textSize":13,"style_textAlign":1,"sys_moduleType":1,"sys_z":5,"sys_w":100,"sys_y":80,"style_textAlpha":"100","sys_x":275,"nPageType":0,"style_textColor":"FFFFFF","nFlag":0,"style_galleryTextAlpha":"100","data_text":"资料","style_bgType":1,"style_bgPic":"","style_textBold":0,"style_bgColor":"1DC6F1","sys_h":30},{"nPageId":"","style_bgAlpha":100,"style_textSize":13,"style_textAlign":1,"sys_moduleType":1,"sys_z":6,"sys_w":87,"sys_y":110,"style_textAlpha":"100","sys_x":188,"nPageType":0,"style_textColor":"FFFFFF","nFlag":0,"style_galleryTextAlpha":"100","data_text":"元素属性","style_bgType":1,"style_bgPic":"","style_textBold":0,"style_bgColor":"C0505D","sys_h":30},{"nPageId":"","style_bgAlpha":100,"style_textSize":13,"style_textAlign":1,"sys_moduleType":1,"sys_z":7,"sys_w":100,"sys_y":110,"style_textAlpha":"100","sys_x":275,"nPageType":0,"style_textColor":"FFFFFF","nFlag":0,"style_galleryTextAlpha":"100","data_text":"冰","style_bgType":1,"style_bgPic":"","style_textBold":0,"style_bgColor":"1DC6F1","sys_h":30},{"nPageId":"","style_bgAlpha":100,"style_textSize":13,"style_textAlign":1,"sys_moduleType":1,"sys_z":8,"sys_w":87,"sys_y":140,"style_textAlpha":"100","sys_x":188,"nPageType":0,"style_textColor":"FFFFFF","nFlag":0,"style_galleryTextAlpha":"100","data_text":"领域","style_bgType":1,"style_bgPic":"","style_textBold":0,"style_bgColor":"C0505D","sys_h":30},{"nPageId":"","style_bgAlpha":100,"style_textSize":13,"style_textAlign":1,"sys_moduleType":1,"sys_z":9,"sys_w":100,"sys_y":140,"style_textAlpha":"100","sys_x":275,"nPageType":0,"style_textColor":"FFFFFF","nFlag":0,"style_galleryTextAlpha":"100","data_text":"NSp","style_bgType":1,"style_bgPic":"","style_textBold":0,"style_bgColor":"1DC6F1","sys_h":30},{"nPageId":"","style_bgAlpha":100,"style_textSize":13,"style_textAlign":1,"sys_moduleType":1,"sys_z":10,"sys_w":87,"sys_y":170,"style_textAlpha":"100","sys_x":188,"nPageType":0,"style_textColor":"FFFFFF","nFlag":0,"style_galleryTextAlpha":"100","data_text":"体型","style_bgType":1,"style_bgPic":"","style_textBold":0,"style_bgColor":"C0505D","sys_h":30},{"nPageId":"","style_bgAlpha":100,"style_textSize":13,"style_textAlign":1,"sys_moduleType":1,"sys_z":11,"sys_w":100,"sys_y":170,"style_textAlpha":"100","sys_x":275,"nPageType":0,"style_textColor":"FFFFFF","nFlag":0,"style_galleryTextAlpha":"100","data_text":"130%/140%","style_bgType":1,"style_bgPic":"","style_textBold":0,"style_bgColor":"1DC6F1","sys_h":30},{"nPageId":"","style_bgAlpha":100,"style_textSize":13,"style_textAlign":1,"sys_moduleType":1,"sys_z":12,"sys_w":76,"sys_y":230,"style_textAlpha":"100","sys_x":112,"nPageType":0,"style_textColor":"FFFFFF","nFlag":0,"style_galleryTextAlpha":"100","data_text":"F1冷却","style_bgType":1,"style_bgPic":"","style_textBold":0,"style_bgColor":"C0505D","sys_h":25},{"nPageId":"","style_bgAlpha":100,"style_textSize":13,"style_textAlign":1,"sys_moduleType":1,"sys_z":13,"sys_w":60,"sys_y":230,"style_textAlpha":"100","sys_x":188,"nPageType":0,"style_textColor":"FFFFFF","nFlag":0,"style_galleryTextAlpha":"100","data_text":"3s","style_bgType":1,"style_bgPic":"","style_textBold":0,"style_bgColor":"9BBB59","sys_h":25},{"nPageId":"","style_bgAlpha":100,"style_textSize":13,"style_textAlign":1,"sys_moduleType":1,"sys_z":14,"sys_w":60,"sys_y":230,"style_textAlpha":"100","sys_x":248,"nPageType":0,"style_textColor":"FFFFFF","nFlag":0,"style_galleryTextAlpha":"100","data_text":"F2冷却","style_bgType":1,"style_bgPic":"","style_textBold":0,"style_bgColor":"C0505D","sys_h":25},{"nPageId":"","style_bgAlpha":100,"style_textSize":13,"style_textAlign":1,"sys_moduleType":1,"sys_z":15,"sys_w":67,"sys_y":230,"style_textAlpha":"100","sys_x":308,"nPageType":0,"style_textColor":"FFFFFF","nFlag":0,"style_galleryTextAlpha":"100","data_text":"6s","style_bgType":1,"style_bgPic":"","style_textBold":0,"style_bgColor":"9BBB59","sys_h":25},{"nPageId":"","style_bgAlpha":100,"style_textSize":13,"style_textAlign":1,"sys_moduleType":1,"sys_z":16,"sys_w":55,"sys_y":230,"style_textAlpha":"100","sys_x":0,"nPageType":0,"style_textColor":"FFFFFF","nFlag":0,"style_galleryTextAlpha":"100","data_text":"AS","style_bgType":1,"style_bgPic":"","style_textBold":0,"style_bgColor":"C0505D","sys_h":25},{"nPageId":"","style_bgAlpha":100,"style_textSize":13,"style_textAlign":1,"sys_moduleType":1,"sys_z":17,"sys_w":57,"sys_y":230,"style_textAlpha":"100","sys_x":55,"nPageType":0,"style_textColor":"FFFFFF","nFlag":0,"style_galleryTextAlpha":"100","data_text":"1.7","style_bgType":1,"style_bgPic":"","style_textBold":0,"style_bgColor":"9BBB59","sys_h":25},{"nPageId":"","style_bgAlpha":100,"style_textSize":13,"style_textAlign":1,"sys_moduleType":1,"sys_z":18,"sys_w":87,"sys_y":200,"style_textAlpha":"100","sys_x":188,"nPageType":0,"style_textColor":"FFFFFF","nFlag":0,"style_galleryTextAlpha":"100","data_text":"身高","style_bgType":1,"style_bgPic":"","style_textBold":0,"style_bgColor":"C0505D","sys_h":30},{"nPageId":"","style_bgAlpha":100,"style_textSize":13,"style_textAlign":1,"sys_moduleType":1,"sys_z":19,"sys_w":100,"sys_y":200,"style_textAlpha":"100","sys_x":275,"nPageType":0,"style_textColor":"FFFFFF","nFlag":0,"style_galleryTextAlpha":"100","data_text":"103cm/111cm","style_bgType":1,"style_bgPic":"","style_textBold":0,"style_bgColor":"1DC6F1","sys_h":30},{"nPageId":"","data_pic":"btn-35.png","style_bigPic":"","sys_moduleType":2,"sys_z":20,"nFlag":0,"sys_w":187,"sys_y":80,"sys_x":188,"sys_h":1,"nPageType":0,"style_eventType":"2"},{"nPageId":"","data_pic":"btn-35.png","style_bigPic":"","sys_moduleType":2,"sys_z":21,"nFlag":0,"sys_w":187,"sys_y":110,"sys_x":188,"sys_h":1,"nPageType":0,"style_eventType":"2"},{"nPageId":"","data_pic":"btn-35.png","style_bigPic":"","sys_moduleType":2,"sys_z":22,"nFlag":0,"sys_w":187,"sys_y":140,"sys_x":188,"sys_h":1,"nPageType":0,"style_eventType":"2"},{"nPageId":"","data_pic":"btn-35.png","style_bigPic":"","sys_moduleType":2,"sys_z":23,"nFlag":0,"sys_w":187,"sys_y":170,"sys_x":188,"sys_h":1,"nPageType":0,"style_eventType":"2"},{"nPageId":"","data_pic":"btn-35.png","style_bigPic":"","sys_moduleType":2,"sys_z":24,"nFlag":0,"sys_w":187,"sys_y":200,"sys_x":188,"sys_h":1,"nPageType":0,"style_eventType":"2"},{"nPageId":"","data_pic":"btn-35.png","style_bigPic":"","sys_moduleType":2,"sys_z":25,"nFlag":0,"sys_w":375,"sys_y":255,"sys_x":0,"sys_h":1,"nPageType":0,"style_eventType":"2"},{"style_textSize":15,"style_textAlign":1,"sys_moduleType":3,"sys_z":26,"sys_w":250,"sys_y":25,"style_textAlpha":"100","sys_x":62,"style_textColor":"FFFFFF","style_galleryTextAlpha":"100","data_text":"Lopmon","style_textBold":0,"sys_h":25},{"nPageId":"","data_pic":"btn-35.png","style_bigPic":"","sys_moduleType":2,"sys_z":27,"nFlag":0,"sys_w":375,"sys_y":230,"sys_x":0,"sys_h":1,"nPageType":0,"style_eventType":"2"},{"nPageId":"","data_pic":"1631802933781_311877.jpg","style_bigPic":"","sys_moduleType":2,"sys_z":28,"nFlag":0,"sys_w":188,"sys_y":50,"sys_x":0,"sys_h":180,"nPageType":0,"style_eventType":"2"},{"nPageId":"","data_pic":"1614618406744_191939.png","style_bigPic":"","sys_moduleType":2,"sys_z":29,"nFlag":0,"sys_w":50,"sys_y":290,"sys_x":8,"sys_h":50,"nPageType":0,"style_eventType":"2"},{"nPageId":"7d501428-3dfb-418b-bdb7-afc902dc5029","data_pic":"1614265861929_382062.png","style_bigPic":"","sys_moduleType":2,"sys_z":30,"nFlag":1,"sys_w":50,"sys_y":290,"sys_x":68,"sys_h":50,"nPageType":0,"style_eventType":"2"},{"nPageId":"05021c02-dedd-49ee-b16e-04ae10a91716","data_pic":"1614265871252_866118.png","style_bigPic":"","sys_moduleType":2,"sys_z":31,"nFlag":1,"sys_w":50,"sys_y":290,"sys_x":128,"sys_h":50,"nPageType":0,"style_eventType":"2"},{"nPageId":"85a5aa83-f575-4d19-b387-2e9783035fd2","data_pic":"1614265874858_595813.png","style_bigPic":"","sys_moduleType":2,"sys_z":32,"nFlag":1,"sys_w":50,"sys_y":290,"sys_x":188,"sys_h":50,"nPageType":0,"style_eventType":"2"},{"nPageId":"c1f2115e-de5b-4ba2-ba89-7ebfee0470c9","data_pic":"1614698759744_1000816.png","style_bigPic":"","sys_moduleType":2,"sys_z":33,"nFlag":1,"sys_w":50,"sys_y":350,"sys_x":68,"sys_h":50,"nPageType":0,"style_eventType":"2"},{"nPageId":"f098a302-5726-479f-a546-285ed3e48f07","data_pic":"1614698240953_773126.png","style_bigPic":"","sys_moduleType":2,"sys_z":34,"nFlag":1,"sys_w":50,"sys_y":350,"sys_x":128,"sys_h":50,"nPageType":0,"style_eventType":"2"},{"nPageId":"f7a942fe-f87d-4274-828d-63dbe09518b1","data_pic":"1614698241159_829329.png","style_bigPic":"","sys_moduleType":2,"sys_z":35,"nFlag":1,"sys_w":50,"sys_y":350,"sys_x":188,"sys_h":50,"nPageType":0,"style_eventType":"2"},{"nPageId":"","style_bgAlpha":100,"style_textSize":13,"style_textAlign":1,"sys_moduleType":1,"sys_z":36,"sys_w":10,"sys_y":340,"style_textAlpha":"100","sys_x":28,"nPageType":0,"style_textColor":"FFFFFF","nFlag":0,"style_galleryTextAlpha":"100","data_text":"","style_bgType":1,"style_bgPic":"","style_textBold":0,"style_bgColor":"FFFF00","sys_h":40},{"nPageId":"","style_bgAlpha":100,"style_textSize":13,"style_textAlign":1,"sys_moduleType":1,"sys_z":37,"sys_w":40,"sys_y":370,"style_textAlpha":"100","sys_x":28,"nPageType":0,"style_textColor":"FFFFFF","nFlag":0,"style_galleryTextAlpha":"100","data_text":"","style_bgType":1,"style_bgPic":"","style_textBold":0,"style_bgColor":"FFFF00","sys_h":10},{"nPageId":"","style_bgAlpha":100,"style_textSize":13,"style_textAlign":1,"sys_moduleType":1,"sys_z":38,"sys_w":10,"sys_y":310,"style_textAlpha":"100","sys_x":118,"nPageType":0,"style_textColor":"FFFFFF","nFlag":0,"style_galleryTextAlpha":"100","data_text":"","style_bgType":1,"style_bgPic":"","style_textBold":0,"style_bgColor":"FFFF00","sys_h":10},{"nPageId":"","style_bgAlpha":100,"style_textSize":13,"style_textAlign":1,"sys_moduleType":1,"sys_z":39,"sys_w":10,"sys_y":310,"style_textAlpha":"100","sys_x":178,"nPageType":0,"style_textColor":"FFFFFF","nFlag":0,"style_galleryTextAlpha":"100","data_text":"","style_bgType":1,"style_bgPic":"","style_textBold":0,"style_bgColor":"FFFF00","sys_h":10},{"nPageId":"","style_bgAlpha":100,"style_textSize":13,"style_textAlign":1,"sys_moduleType":1,"sys_z":40,"sys_w":10,"sys_y":370,"style_textAlpha":"100","sys_x":118,"nPageType":0,"style_textColor":"FFFFFF","nFlag":0,"style_galleryTextAlpha":"100","data_text":"","style_bgType":1,"style_bgPic":"","style_textBold":0,"style_bgColor":"FFFF00","sys_h":10},{"nPageId":"","style_bgAlpha":100,"style_textSize":13,"style_textAlign":1,"sys_moduleType":1,"sys_z":41,"sys_w":10,"sys_y":370,"style_textAlpha":"100","sys_x":178,"nPageType":0,"style_textColor":"FFFFFF","nFlag":0,"style_galleryTextAlpha":"100","data_text":"","style_bgType":1,"style_bgPic":"","style_textBold":0,"style_bgColor":"FFFF00","sys_h":10},{"nPageId":"","style_bgAlpha":100,"style_textSize":13,"style_textAlign":1,"sys_moduleType":1,"sys_z":42,"sys_w":10,"sys_y":310,"style_textAlpha":"100","sys_x":58,"nPageType":0,"style_textColor":"FFFFFF","nFlag":0,"style_galleryTextAlpha":"100","data_text":"","style_bgType":1,"style_bgPic":"","style_textBold":0,"style_bgColor":"FFFF00","sys_h":10},{"nPageId":"","style_bgAlpha":100,"style_textSize":13,"style_textAlign":1,"sys_moduleType":1,"sys_z":43,"sys_w":10,"sys_y":400,"style_textAlpha":"100","sys_x":208,"nPageType":0,"style_textColor":"FFFFFF","nFlag":0,"style_galleryTextAlpha":"100","data_text":"","style_bgType":1,"style_bgPic":"","style_textBold":0,"style_bgColor":"FF0000","sys_h":10},{"nPageId":"1f5a696e-3fcf-4fee-8e48-40768a22bc19","data_pic":"1641182923106_761832.png","style_bigPic":"","sys_moduleType":2,"sys_z":44,"nFlag":1,"sys_w":50,"sys_y":410,"sys_x":188,"sys_h":50,"nPageType":0,"style_eventType":"2"},{"nPageId":"","style_bgAlpha":100,"style_textSize":13,"style_textAlign":1,"sys_moduleType":1,"sys_z":45,"sys_w":10,"sys_y":430,"style_textAlpha":"100","sys_x":238,"nPageType":0,"style_textColor":"FFFFFF","nFlag":0,"style_galleryTextAlpha":"100","data_text":"","style_bgType":1,"style_bgPic":"","style_textBold":0,"style_bgColor":"FF0000","sys_h":10},{"nPageId":"1ac5f89a-f22d-4f72-abdc-5d2f9531a665","data_pic":"1641182918532_993232.png","style_bigPic":"","sys_moduleType":2,"sys_z":46,"nFlag":1,"sys_w":50,"sys_y":410,"sys_x":248,"sys_h":50,"nPageType":0,"style_eventType":"2"},{"nPageId":"","style_bgAlpha":100,"style_textSize":13,"style_textAlign":1,"sys_moduleType":1,"sys_z":47,"sys_w":40,"sys_y":310,"style_textAlpha":"100","sys_x":238,"nPageType":0,"style_textColor":"FFFFFF","nFlag":0,"style_galleryTextAlpha":"100","data_text":"","style_bgType":1,"style_bgPic":"","style_textBold":0,"style_bgColor":"FF0000","sys_h":10},{"nPageId":"","style_bgAlpha":100,"style_textSize":13,"style_textAlign":1,"sys_moduleType":1,"sys_z":48,"sys_w":10,"sys_y":310,"style_textAlpha":"100","sys_x":268,"nPageType":0,"style_textColor":"FFFFFF","nFlag":0,"style_galleryTextAlpha":"100","data_text":"","style_bgType":1,"style_bgPic":"","style_textBold":0,"style_bgColor":"FF0000","sys_h":100}],"style_tFlag":0,"style_tNavID":"","sys_pageID":"0ca6e74b-f043-44e4-871f-a7968125f6b6","itemNew":"","data_password":"","style_bNavType":2001,"itemName":"","style_bFlag":0,"style_bNavID":"","style_bgType":2,"style_bgPic":"btn-28.jpg","style_bgColor":"FFFFFF","style_tNavType":1001}