{"data_pageName":"","style_bgAlpha":100,"data_shoppingFloat":"","item":[{"style_textSize":20,"style_textAlign":1,"sys_moduleType":3,"sys_z":0,"sys_w":160,"sys_y":0,"style_textAlpha":"100","sys_x":107,"style_textColor":"FFFFFF","style_galleryTextAlpha":"100","data_text":"首饰单项最大值","style_textBold":0,"sys_h":40},{"nPageId":null,"style_bgAlpha":100,"style_textSize":13,"style_textAlign":1,"sys_moduleType":1,"sys_z":1,"sys_w":100,"sys_y":5,"style_textAlpha":"100","sys_x":7,"nPageType":3,"style_textColor":"FFFFFF","nFlag":1,"style_galleryTextAlpha":"100","data_text":"上一页","style_bgType":1,"style_bgPic":"","style_textBold":0,"style_bgColor":"1DC6F1","sys_h":30},{"nPageId":"3a73c563-659f-4dac-911b-0ac9d1a48dd7","style_bgAlpha":100,"style_textSize":12,"style_textAlign":1,"sys_moduleType":1,"sys_z":2,"sys_w":60,"sys_y":80,"style_textAlpha":"100","sys_x":38,"nPageType":0,"style_textColor":"FFFFFF","nFlag":1,"style_galleryTextAlpha":"100","data_text":"4和5能力","style_bgType":2,"style_bgPic":"1617108614695_514114.png","style_textBold":0,"style_bgColor":"FC8BC8","sys_h":60},{"nPageId":"7443682d-24a7-437c-8197-d72c6fe4d85b","style_bgAlpha":100,"style_textSize":12,"style_textAlign":1,"sys_moduleType":1,"sys_z":3,"sys_w":60,"sys_y":80,"style_textAlpha":"100","sys_x":98,"nPageType":0,"style_textColor":"FFFFFF","nFlag":1,"style_galleryTextAlpha":"100","data_text":"4和5能力","style_bgType":2,"style_bgPic":"1617108614855_328511.png","style_textBold":0,"style_bgColor":"1DC6F1","sys_h":60},{"nPageId":"37f5fc5b-fe5e-4d46-a32e-570ea937c2a2","style_bgAlpha":100,"style_textSize":10,"style_textAlign":1,"sys_moduleType":1,"sys_z":4,"sys_w":60,"sys_y":80,"style_textAlpha":"100","sys_x":158,"nPageType":0,"style_textColor":"FFFFFF","nFlag":1,"style_galleryTextAlpha":"100","data_text":"2必杀1命中","style_bgType":2,"style_bgPic":"1629291208053_1026235.png","style_textBold":0,"style_bgColor":"F79646","sys_h":60},{"nPageId":"f25abeb5-88ea-45b9-93f3-35611a0ee504","style_bgAlpha":100,"style_textSize":12,"style_textAlign":1,"sys_moduleType":1,"sys_z":5,"sys_w":60,"sys_y":260,"style_textAlpha":"100","sys_x":218,"nPageType":0,"style_textColor":"FFFFFF","nFlag":1,"style_galleryTextAlpha":"100","data_text":"4能力","style_bgType":2,"style_bgPic":"1617108760312_107815.png","style_textBold":0,"style_bgColor":"8064A2","sys_h":60},{"nPageId":"7fa43b0c-2982-4488-aa89-9a7115bb2059","style_bgAlpha":100,"style_textSize":11,"style_textAlign":1,"sys_moduleType":1,"sys_z":6,"sys_w":60,"sys_y":200,"style_textAlpha":"100","sys_x":218,"nPageType":0,"style_textColor":"FFFFFF","nFlag":1,"style_galleryTextAlpha":"100","data_text":"皇家5能力","style_bgType":2,"style_bgPic":"1617109011329_190577.png","style_textBold":0,"style_bgColor":"5F497A","sys_h":60},{"nPageId":"004aebeb-1efb-42dd-a023-5d2851457215","style_bgAlpha":100,"style_textSize":12,"style_textAlign":1,"sys_moduleType":1,"sys_z":7,"sys_w":60,"sys_y":80,"style_textAlpha":"100","sys_x":218,"nPageType":0,"style_textColor":"FFFFFF","nFlag":1,"style_galleryTextAlpha":"100","data_text":"金红","style_bgType":2,"style_bgPic":"1617108911577_925630.png","style_textBold":0,"style_bgColor":"5F497A","sys_h":60},{"style_textSize":13,"style_textAlign":1,"sys_moduleType":3,"sys_z":8,"sys_w":60,"sys_y":50,"style_textAlpha":"100","sys_x":38,"style_textColor":"FFFFFF","style_galleryTextAlpha":"100","data_text":"戒指","style_textBold":0,"sys_h":30},{"style_textSize":13,"style_textAlign":1,"sys_moduleType":3,"sys_z":9,"sys_w":60,"sys_y":50,"style_textAlpha":"100","sys_x":98,"style_textColor":"FFFFFF","style_galleryTextAlpha":"100","data_text":"项链","style_textBold":0,"sys_h":30},{"style_textSize":13,"style_textAlign":1,"sys_moduleType":3,"sys_z":10,"sys_w":60,"sys_y":50,"style_textAlpha":"100","sys_x":158,"style_textColor":"FFFFFF","style_galleryTextAlpha":"100","data_text":"耳环","style_textBold":0,"sys_h":30},{"style_textSize":13,"style_textAlign":1,"sys_moduleType":3,"sys_z":11,"sys_w":60,"sys_y":50,"style_textAlpha":"100","sys_x":218,"style_textColor":"FFFFFF","style_galleryTextAlpha":"100","data_text":"手环","style_textBold":0,"sys_h":30},{"style_textSize":12,"style_textAlign":1,"sys_moduleType":3,"sys_z":12,"sys_w":70,"sys_y":50,"style_textAlpha":"100","sys_x":273,"style_textColor":"FFFFFF","style_galleryTextAlpha":"100","data_text":"属性暴龙机","style_textBold":0,"sys_h":30},{"nPageId":"e6ee130d-9eae-4607-90e2-78b04ab17b66","style_bgAlpha":100,"style_textSize":12,"style_textAlign":1,"sys_moduleType":1,"sys_z":13,"sys_w":60,"sys_y":200,"style_textAlpha":"100","sys_x":278,"nPageType":0,"style_textColor":"FFFFFF","nFlag":1,"style_galleryTextAlpha":"100","data_text":"二卡","style_bgType":2,"style_bgPic":"1617107470681_916456.png","style_textBold":0,"style_bgColor":"8064A2","sys_h":60},{"nPageId":"5c1d20d4-4316-4839-ac34-81627fac8beb","style_bgAlpha":100,"style_textSize":12,"style_textAlign":1,"sys_moduleType":1,"sys_z":14,"sys_w":60,"sys_y":80,"style_textAlpha":"100","sys_x":278,"nPageType":0,"style_textColor":"FFFFFF","nFlag":1,"style_galleryTextAlpha":"100","data_text":"四卡","style_bgType":2,"style_bgPic":"1616939441491_1049524.png","style_textBold":0,"style_bgColor":"8064A2","sys_h":60},{"nPageId":"01951152-e849-48b1-a2a5-19fc5061ad44","style_bgAlpha":100,"style_textSize":12,"style_textAlign":1,"sys_moduleType":1,"sys_z":15,"sys_w":60,"sys_y":140,"style_textAlpha":"100","sys_x":278,"nPageType":0,"style_textColor":"000000","nFlag":1,"style_galleryTextAlpha":"100","data_text":"三卡","style_bgType":2,"style_bgPic":"1616937872012_341819.png","style_textBold":0,"style_bgColor":"8064A2","sys_h":60},{"nPageId":"bad932be-ebfc-4bb8-a272-ab00dcf4f49a","style_bgAlpha":100,"style_textSize":12,"style_textAlign":1,"sys_moduleType":1,"sys_z":16,"sys_w":60,"sys_y":140,"style_textAlpha":"100","sys_x":218,"nPageType":0,"style_textColor":"FFFFFF","nFlag":1,"style_galleryTextAlpha":"100","data_text":"奇迹9阶","style_bgType":2,"style_bgPic":"1617108911411_608071.png","style_textBold":0,"style_bgColor":"5F497A","sys_h":60},{"nPageId":"37e67f75-eb96-4a24-bfdb-1b2c89a937f6","style_bgAlpha":100,"style_textSize":10,"style_textAlign":1,"sys_moduleType":1,"sys_z":17,"sys_w":60,"sys_y":200,"style_textAlpha":"100","sys_x":158,"nPageType":0,"style_textColor":"FFFFFF","nFlag":1,"style_galleryTextAlpha":"100","data_text":"金耳环","style_bgType":2,"style_bgPic":"1617108976984_746685.png","style_textBold":0,"style_bgColor":"F79646","sys_h":60},{"nPageId":"581041ce-7c46-44a9-8809-a6df9005fa46","style_bgAlpha":100,"style_textSize":10,"style_textAlign":1,"sys_moduleType":1,"sys_z":18,"sys_w":60,"sys_y":140,"style_textAlpha":"100","sys_x":158,"nPageType":0,"style_textColor":"FFFFFF","nFlag":1,"style_galleryTextAlpha":"100","data_text":"1必杀2命中","style_bgType":2,"style_bgPic":"1617108911662_581726.png","style_textBold":0,"style_bgColor":"F79646","sys_h":60},{"nPageId":"797ab0f3-a8d3-4e84-a8bd-53256a11397a","style_bgAlpha":100,"style_textSize":12,"style_textAlign":1,"sys_moduleType":1,"sys_z":19,"sys_w":60,"sys_y":320,"style_textAlpha":"100","sys_x":38,"nPageType":0,"style_textColor":"FFFFFF","nFlag":1,"style_galleryTextAlpha":"100","data_text":"黄龙10级","style_bgType":2,"style_bgPic":"1653043155790_939046.png","style_textBold":0,"style_bgColor":"FC8BC8","sys_h":60},{"nPageId":"8d7617cc-eeee-4ba3-84ed-e1017a8bb0ab","style_bgAlpha":100,"style_textSize":12,"style_textAlign":1,"sys_moduleType":1,"sys_z":20,"sys_w":60,"sys_y":320,"style_textAlpha":"100","sys_x":98,"nPageType":0,"style_textColor":"FFFFFF","nFlag":1,"style_galleryTextAlpha":"100","data_text":"黄龙10级","style_bgType":2,"style_bgPic":"1653043155937_267826.png","style_textBold":0,"style_bgColor":"FC8BC8","sys_h":60},{"nPageId":"be9745da-19fa-4670-a620-afcb600e7477","style_bgAlpha":100,"style_textSize":12,"style_textAlign":1,"sys_moduleType":1,"sys_z":21,"sys_w":60,"sys_y":320,"style_textAlpha":"100","sys_x":158,"nPageType":0,"style_textColor":"FFFFFF","nFlag":1,"style_galleryTextAlpha":"100","data_text":"黄龙10级","style_bgType":2,"style_bgPic":"1653043156076_251984.png","style_textBold":0,"style_bgColor":"FC8BC8","sys_h":60},{"nPageId":"327a0a22-8f56-4fd7-a816-aa7729856469","style_bgAlpha":100,"style_textSize":11,"style_textAlign":1,"sys_moduleType":1,"sys_z":22,"sys_w":60,"sys_y":380,"style_textAlpha":"100","sys_x":38,"nPageType":0,"style_textColor":"FFFFFF","nFlag":1,"style_galleryTextAlpha":"100","data_text":"四圣闪5级","style_bgType":2,"style_bgPic":"1653043274226_723467.png","style_textBold":0,"style_bgColor":"FC8BC8","sys_h":60},{"nPageId":"b6457236-7a56-462d-929a-fc0130d8b260","style_bgAlpha":100,"style_textSize":11,"style_textAlign":1,"sys_moduleType":1,"sys_z":23,"sys_w":60,"sys_y":380,"style_textAlpha":"100","sys_x":98,"nPageType":0,"style_textColor":"FFFFFF","nFlag":1,"style_galleryTextAlpha":"100","data_text":"四圣闪5级","style_bgType":2,"style_bgPic":"1653043274194_504897.png","style_textBold":0,"style_bgColor":"FC8BC8","sys_h":60},{"nPageId":"3f8a1cd2-ef07-4582-98ce-9d471d09c4ac","style_bgAlpha":100,"style_textSize":11,"style_textAlign":1,"sys_moduleType":1,"sys_z":24,"sys_w":60,"sys_y":380,"style_textAlpha":"100","sys_x":158,"nPageType":0,"style_textColor":"FFFFFF","nFlag":1,"style_galleryTextAlpha":"100","data_text":"四圣闪5级","style_bgType":2,"style_bgPic":"1653043274155_461976.png","style_textBold":0,"style_bgColor":"FC8BC8","sys_h":60}],"style_tFlag":0,"style_tNavID":"","sys_pageID":"7b1f07fb-e786-44a0-b872-f3f2aef155de","itemNew":"","data_password":"","style_bNavType":2001,"itemName":"","style_bFlag":0,"style_bNavID":"","style_bgType":2,"style_bgPic":"btn-28.jpg","style_bgColor":"FFFFFF","style_tNavType":1001}